django_sql_log/middleware.py
django_sql_log/__init__.py
django_sql_log-1.2.1.dist-info/WHEEL
django_sql_log-1.2.1.dist-info/metadata.json
django_sql_log-1.2.1.dist-info/METADATA
django_sql_log-1.2.1.dist-info/RECORD
django_sql_log-1.2.1.dist-info/DESCRIPTION.rst
django_sql_log-1.2.1.dist-info/top_level.txt
