Metadata-Version: 2.0
Name: django-sql-log
Version: 1.2.1
Summary: Write Start/Stop events in your SQL logs.
Home-page: https://github.com/novafloss/django-sql-log
Author: Novapost
Author-email: bruno.bord@novapost.fr
License: UNKNOWN
Keywords: django SQL log postgresql
Platform: UNKNOWN
Classifier: Development Status :: 4 - Beta
Classifier: Environment :: Web Environment
Classifier: Framework :: Django
Classifier: Intended Audience :: Developers
Classifier: License :: OSI Approved :: MIT License
Classifier: Operating System :: OS Independent
Classifier: Programming Language :: Python
Classifier: Topic :: Database
Classifier: Topic :: System :: Logging
Requires-Dist: Django
